Metadata-Version: 1.0
Name: dsnd-probabilitysk1905
Version: 0.1
Summary: Gaussian and Binomial distributions
Home-page: UNKNOWN
Author: Shreya Kanodia
Author-email: shreyakanodia19@gmail.com
License: UNKNOWN
Platform: UNKNOWN
